{
     "Task0": [
          7,
          336,
          90,
          446
     ],
     "Task1": [
          7,
          342,
          32,
          407
     ],
     "Task2": [
          10,
          336,
          92,
          470
     ],
     "Task3": [
          6,
          348,
          18,
          492
     ],
     "Task4": [
          9,
          336,
          24,
          409
     ],
     "Task5": [
          7,
          342,
          53,
          457
     ],
     "Task6": [
          11,
          348,
          12,
          483
     ],
     "Task7": [
          2,
          342,
          81,
          494
     ],
     "Task8": [
          6,
          342,
          9,
          468
     ],
     "Task9": [
          8,
          336,
          66,
          445
     ],
     "Task10": [
          8,
          342,
          12,
          455
     ],
     "Task11": [
          1,
          342,
          81,
          424
     ],
     "Task12": [
          8,
          342,
          52,
          408
     ],
     "Task13": [
          3,
          342,
          50,
          419
     ],
     "Task14": [
          10,
          348,
          12,
          475
     ],
     "Task15": [
          3,
          342,
          94,
          441
     ],
     "Task16": [
          10,
          348,
          36,
          421
     ],
     "Task17": [
          7,
          336,
          88,
          439
     ],
     "Task18": [
          3,
          342,
          69,
          449
     ],
     "Task19": [
          1,
          342,
          26,
          485
     ],
     "Task20": [
          5,
          348,
          9,
          469
     ],
     "Task21": [
          7,
          342,
          85,
          476
     ],
     "Task22": [
          11,
          342,
          23,
          405
     ],
     "Task23": [
          9,
          336,
          99,
          435
     ],
     "Task24": [
          3,
          342,
          89,
          492
     ],
     "Task25": [
          7,
          336,
          91,
          491
     ],
     "Task26": [
          6,
          348,
          18,
          404
     ],
     "Task27": [
          10,
          342,
          73,
          400
     ],
     "Task28": [
          6,
          342,
          36,
          449
     ],
     "Task29": [
          10,
          342,
          52,
          421
     ],
     "Task30": [
          3,
          348,
          93,
          432
     ],
     "Task31": [
          1,
          348,
          94,
          446
     ],
     "Task32": [
          2,
          348,
          34,
          500
     ],
     "Task33": [
          6,
          336,
          35,
          471
     ],
     "Task34": [
          1,
          348,
          32,
          421
     ],
     "Task35": [
          1,
          342,
          52,
          489
     ],
     "Task36": [
          2,
          348,
          89,
          466
     ],
     "Task37": [
          9,
          342,
          76,
          459
     ],
     "Task38": [
          11,
          348,
          7,
          480
     ],
     "Task39": [
          6,
          348,
          13,
          482
     ],
     "Task40": [
          11,
          336,
          71,
          421
     ],
     "Task41": [
          11,
          336,
          84,
          485
     ],
     "Task42": [
          2,
          336,
          88,
          409
     ],
     "Task43": [
          11,
          342,
          61,
          403
     ],
     "Task44": [
          5,
          342,
          75,
          435
     ],
     "Task45": [
          3,
          348,
          83,
          493
     ],
     "Task46": [
          4,
          342,
          44,
          408
     ],
     "Task47": [
          10,
          348,
          83,
          429
     ],
     "Task48": [
          11,
          348,
          89,
          442
     ],
     "Task49": [
          11,
          342,
          65,
          475
     ],
     "Task50": [
          1,
          348,
          53,
          490
     ],
     "Task51": [
          11,
          336,
          72,
          416
     ],
     "Task52": [
          6,
          342,
          52,
          449
     ],
     "Task53": [
          2,
          342,
          8,
          457
     ],
     "Task54": [
          7,
          342,
          96,
          475
     ],
     "Task55": [
          11,
          342,
          77,
          473
     ],
     "Task56": [
          8,
          348,
          46,
          411
     ],
     "Task57": [
          8,
          348,
          56,
          440
     ],
     "Task58": [
          9,
          336,
          67,
          451
     ],
     "Task59": [
          2,
          336,
          49,
          429
     ],
     "Task60": [
          11,
          342,
          40,
          426
     ],
     "Task61": [
          5,
          348,
          22,
          482
     ],
     "Task62": [
          8,
          336,
          49,
          400
     ],
     "Task63": [
          3,
          336,
          79,
          421
     ],
     "Task64": [
          11,
          336,
          1,
          467
     ],
     "Task65": [
          4,
          348,
          62,
          478
     ],
     "Task66": [
          8,
          342,
          29,
          474
     ],
     "Task67": [
          1,
          342,
          33,
          498
     ],
     "Task68": [
          5,
          348,
          81,
          402
     ],
     "Task69": [
          8,
          336,
          1,
          437
     ],
     "Task70": [
          7,
          348,
          33,
          490
     ],
     "Task71": [
          9,
          342,
          63,
          428
     ],
     "Task72": [
          1,
          342,
          89,
          497
     ],
     "Task73": [
          6,
          336,
          93,
          437
     ],
     "Task74": [
          11,
          342,
          7,
          500
     ],
     "Task75": [
          10,
          336,
          5,
          479
     ],
     "Task76": [
          1,
          348,
          69,
          432
     ],
     "Task77": [
          2,
          342,
          15,
          410
     ],
     "Task78": [
          7,
          348,
          80,
          438
     ],
     "Task79": [
          1,
          342,
          49,
          486
     ],
     "Task80": [
          10,
          348,
          3,
          432
     ],
     "Task81": [
          8,
          348,
          19,
          483
     ],
     "Task82": [
          1,
          342,
          81,
          439
     ],
     "Task83": [
          8,
          342,
          41,
          431
     ],
     "Task84": [
          11,
          336,
          22,
          476
     ],
     "Task85": [
          9,
          336,
          89,
          477
     ],
     "Task86": [
          4,
          336,
          78,
          430
     ],
     "Task87": [
          3,
          348,
          39,
          435
     ],
     "Task88": [
          2,
          348,
          94,
          423
     ],
     "Task89": [
          6,
          348,
          89,
          463
     ],
     "Task90": [
          4,
          342,
          77,
          435
     ],
     "Task91": [
          10,
          348,
          45,
          406
     ],
     "Task92": [
          4,
          348,
          90,
          430
     ],
     "Task93": [
          8,
          342,
          74,
          407
     ],
     "Task94": [
          4,
          348,
          46,
          467
     ],
     "Task95": [
          9,
          342,
          94,
          441
     ],
     "Task96": [
          4,
          336,
          83,
          453
     ],
     "Task97": [
          9,
          336,
          33,
          447
     ],
     "Task98": [
          3,
          342,
          50,
          470
     ],
     "Task99": [
          3,
          336,
          35,
          469
     ],
     "Task100": [
          9,
          336,
          77,
          490
     ],
     "Task101": [
          10,
          336,
          70,
          482
     ],
     "Task102": [
          5,
          348,
          60,
          490
     ],
     "Task103": [
          9,
          348,
          66,
          465
     ],
     "Task104": [
          1,
          342,
          48,
          465
     ],
     "Task105": [
          4,
          342,
          60,
          498
     ],
     "Task106": [
          4,
          336,
          52,
          479
     ],
     "Task107": [
          11,
          336,
          62,
          482
     ],
     "Task108": [
          10,
          342,
          42,
          415
     ],
     "Task109": [
          7,
          336,
          87,
          437
     ],
     "Task110": [
          4,
          348,
          90,
          407
     ],
     "Task111": [
          3,
          348,
          51,
          443
     ],
     "Task112": [
          3,
          336,
          35,
          463
     ],
     "Task113": [
          4,
          342,
          1,
          455
     ],
     "Task114": [
          11,
          336,
          3,
          453
     ],
     "Task115": [
          6,
          336,
          90,
          489
     ],
     "Task116": [
          3,
          342,
          51,
          426
     ],
     "Task117": [
          5,
          342,
          41,
          423
     ],
     "Task118": [
          5,
          336,
          26,
          491
     ],
     "Task119": [
          11,
          342,
          59,
          462
     ],
     "Task120": [
          8,
          336,
          59,
          475
     ],
     "Task121": [
          3,
          336,
          67,
          498
     ],
     "Task122": [
          7,
          336,
          34,
          457
     ],
     "Task123": [
          2,
          348,
          8,
          465
     ],
     "Task124": [
          2,
          342,
          23,
          404
     ],
     "Task125": [
          2,
          336,
          19,
          423
     ],
     "Task126": [
          3,
          336,
          57,
          439
     ],
     "Task127": [
          5,
          336,
          56,
          454
     ],
     "Task128": [
          7,
          336,
          11,
          426
     ],
     "Task129": [
          4,
          336,
          48,
          431
     ],
     "Task130": [
          11,
          336,
          50,
          486
     ],
     "Task131": [
          10,
          342,
          60,
          410
     ],
     "Task132": [
          7,
          342,
          15,
          448
     ],
     "Task133": [
          11,
          342,
          48,
          488
     ],
     "Task134": [
          5,
          348,
          37,
          466
     ],
     "Task135": [
          6,
          336,
          45,
          437
     ],
     "Task136": [
          5,
          348,
          41,
          500
     ],
     "Task137": [
          2,
          342,
          35,
          462
     ],
     "Task138": [
          2,
          336,
          33,
          472
     ],
     "Task139": [
          11,
          348,
          23,
          427
     ],
     "Task140": [
          6,
          342,
          28,
          496
     ],
     "Task141": [
          4,
          336,
          45,
          428
     ],
     "Task142": [
          9,
          342,
          60,
          483
     ],
     "Task143": [
          3,
          336,
          93,
          491
     ],
     "Task144": [
          8,
          348,
          35,
          498
     ],
     "Task145": [
          6,
          336,
          4,
          474
     ],
     "Task146": [
          5,
          342,
          90,
          433
     ],
     "Task147": [
          1,
          342,
          36,
          469
     ],
     "Task148": [
          10,
          348,
          52,
          423
     ],
     "Task149": [
          6,
          342,
          87,
          430
     ],
     "Task150": [
          1,
          342,
          0,
          434
     ],
     "Task151": [
          11,
          336,
          34,
          500
     ],
     "Task152": [
          5,
          336,
          60,
          500
     ],
     "Task153": [
          3,
          342,
          38,
          404
     ],
     "Task154": [
          10,
          342,
          38,
          485
     ],
     "Task155": [
          3,
          342,
          93,
          425
     ],
     "Task156": [
          10,
          348,
          87,
          466
     ],
     "Task157": [
          8,
          348,
          44,
          495
     ],
     "Task158": [
          9,
          342,
          71,
          487
     ],
     "Task159": [
          11,
          336,
          30,
          448
     ],
     "Task160": [
          9,
          348,
          57,
          468
     ],
     "Task161": [
          7,
          348,
          2,
          421
     ],
     "Task162": [
          4,
          342,
          87,
          439
     ],
     "Task163": [
          1,
          348,
          64,
          453
     ],
     "Task164": [
          5,
          336,
          85,
          467
     ],
     "Task165": [
          5,
          336,
          37,
          422
     ],
     "Task166": [
          2,
          342,
          86,
          459
     ],
     "Task167": [
          6,
          336,
          96,
          487
     ],
     "Task168": [
          5,
          342,
          73,
          500
     ],
     "Task169": [
          6,
          336,
          45,
          413
     ],
     "Task170": [
          6,
          342,
          42,
          418
     ],
     "Task171": [
          3,
          342,
          76,
          427
     ],
     "Task172": [
          10,
          336,
          58,
          476
     ],
     "Task173": [
          3,
          348,
          68,
          409
     ],
     "Task174": [
          6,
          336,
          81,
          436
     ],
     "Task175": [
          2,
          342,
          76,
          442
     ],
     "Task176": [
          1,
          348,
          29,
          484
     ],
     "Task177": [
          8,
          336,
          60,
          488
     ],
     "Task178": [
          3,
          342,
          69,
          419
     ],
     "Task179": [
          10,
          342,
          30,
          404
     ],
     "Task180": [
          4,
          336,
          0,
          428
     ],
     "Task181": [
          3,
          342,
          10,
          456
     ],
     "Task182": [
          6,
          336,
          39,
          476
     ],
     "Task183": [
          1,
          342,
          51,
          452
     ],
     "Task184": [
          11,
          348,
          17,
          475
     ],
     "Task185": [
          1,
          342,
          21,
          442
     ],
     "Task186": [
          1,
          336,
          20,
          407
     ],
     "Task187": [
          4,
          342,
          13,
          476
     ],
     "Task188": [
          1,
          342,
          63,
          436
     ],
     "Task189": [
          1,
          348,
          88,
          419
     ],
     "Task190": [
          2,
          342,
          98,
          477
     ],
     "Task191": [
          10,
          342,
          10,
          406
     ],
     "Task192": [
          2,
          342,
          26,
          428
     ],
     "Task193": [
          8,
          336,
          87,
          430
     ],
     "Task194": [
          9,
          336,
          9,
          471
     ],
     "Task195": [
          11,
          342,
          36,
          492
     ],
     "Task196": [
          11,
          336,
          27,
          462
     ],
     "Task197": [
          2,
          336,
          40,
          414
     ],
     "Task198": [
          1,
          342,
          25,
          445
     ],
     "Task199": [
          8,
          348,
          31,
          461
     ],
     "Task200": [
          9,
          348,
          77,
          480
     ],
     "Task201": [
          6,
          336,
          23,
          441
     ],
     "Task202": [
          5,
          336,
          73,
          449
     ],
     "Task203": [
          5,
          336,
          41,
          493
     ],
     "Task204": [
          8,
          336,
          47,
          483
     ],
     "Task205": [
          4,
          336,
          44,
          401
     ],
     "Task206": [
          4,
          348,
          38,
          484
     ],
     "Task207": [
          2,
          342,
          39,
          463
     ],
     "Task208": [
          5,
          336,
          10,
          434
     ],
     "Task209": [
          3,
          342,
          80,
          480
     ],
     "Task210": [
          3,
          342,
          2,
          429
     ],
     "Task211": [
          2,
          336,
          97,
          420
     ],
     "Task212": [
          2,
          342,
          76,
          402
     ],
     "Task213": [
          11,
          342,
          86,
          495
     ],
     "Task214": [
          6,
          336,
          70,
          465
     ],
     "Task215": [
          8,
          342,
          69,
          499
     ],
     "Task216": [
          1,
          348,
          68,
          442
     ],
     "Task217": [
          1,
          342,
          15,
          489
     ],
     "Task218": [
          5,
          336,
          3,
          424
     ],
     "Task219": [
          10,
          342,
          11,
          421
     ],
     "Task220": [
          7,
          336,
          35,
          456
     ],
     "Task221": [
          3,
          342,
          97,
          447
     ],
     "Task222": [
          7,
          342,
          54,
          429
     ],
     "Task223": [
          5,
          336,
          13,
          442
     ],
     "Task224": [
          8,
          342,
          71,
          446
     ],
     "Task225": [
          8,
          342,
          12,
          457
     ],
     "Task226": [
          3,
          336,
          70,
          471
     ],
     "Task227": [
          8,
          336,
          52,
          459
     ],
     "Task228": [
          6,
          342,
          33,
          433
     ],
     "Task229": [
          4,
          336,
          58,
          469
     ],
     "Task230": [
          7,
          336,
          73,
          468
     ],
     "Task231": [
          6,
          348,
          75,
          415
     ],
     "Task232": [
          9,
          342,
          3,
          472
     ],
     "Task233": [
          2,
          348,
          8,
          407
     ],
     "Task234": [
          9,
          348,
          92,
          402
     ],
     "Task235": [
          9,
          336,
          4,
          454
     ],
     "Task236": [
          7,
          336,
          72,
          457
     ],
     "Task237": [
          5,
          342,
          68,
          472
     ],
     "Task238": [
          2,
          336,
          32,
          496
     ],
     "Task239": [
          10,
          348,
          92,
          479
     ],
     "Task240": [
          3,
          348,
          84,
          465
     ],
     "Task241": [
          9,
          336,
          99,
          449
     ],
     "Task242": [
          2,
          342,
          38,
          423
     ],
     "Task243": [
          11,
          342,
          65,
          430
     ],
     "Task244": [
          4,
          342,
          99,
          477
     ],
     "Task245": [
          5,
          342,
          56,
          492
     ],
     "Task246": [
          4,
          348,
          85,
          439
     ],
     "Task247": [
          10,
          348,
          12,
          489
     ],
     "Task248": [
          3,
          348,
          40,
          496
     ],
     "Task249": [
          5,
          342,
          53,
          498
     ],
     "Task250": [
          8,
          342,
          31,
          441
     ],
     "Task251": [
          10,
          336,
          18,
          484
     ],
     "Task252": [
          2,
          336,
          15,
          401
     ],
     "Task253": [
          10,
          336,
          82,
          448
     ],
     "Task254": [
          7,
          336,
          80,
          458
     ],
     "Task255": [
          1,
          348,
          77,
          404
     ],
     "Task256": [
          7,
          336,
          16,
          403
     ],
     "Task257": [
          9,
          348,
          97,
          447
     ],
     "Task258": [
          3,
          336,
          8,
          481
     ],
     "Task259": [
          3,
          342,
          47,
          471
     ],
     "Task260": [
          5,
          342,
          76,
          467
     ],
     "Task261": [
          7,
          336,
          90,
          460
     ],
     "Task262": [
          7,
          336,
          42,
          420
     ],
     "Task263": [
          7,
          342,
          36,
          408
     ],
     "Task264": [
          9,
          336,
          38,
          420
     ],
     "Task265": [
          3,
          336,
          59,
          475
     ],
     "Task266": [
          5,
          342,
          98,
          491
     ],
     "Task267": [
          3,
          336,
          97,
          411
     ],
     "Task268": [
          11,
          336,
          43,
          428
     ],
     "Task269": [
          10,
          348,
          93,
          492
     ],
     "Task270": [
          3,
          342,
          18,
          405
     ],
     "Task271": [
          4,
          342,
          68,
          465
     ],
     "Task272": [
          1,
          336,
          40,
          415
     ],
     "Task273": [
          5,
          348,
          100,
          468
     ],
     "Task274": [
          6,
          336,
          20,
          465
     ],
     "Task275": [
          7,
          348,
          81,
          426
     ],
     "Task276": [
          1,
          348,
          74,
          493
     ],
     "Task277": [
          2,
          342,
          63,
          478
     ],
     "Task278": [
          8,
          348,
          63,
          458
     ],
     "Task279": [
          11,
          342,
          23,
          499
     ],
     "Task280": [
          9,
          342,
          80,
          493
     ],
     "Task281": [
          4,
          348,
          78,
          450
     ],
     "Task282": [
          1,
          336,
          98,
          480
     ],
     "Task283": [
          3,
          342,
          37,
          467
     ],
     "Task284": [
          1,
          348,
          69,
          490
     ],
     "Task285": [
          8,
          336,
          69,
          479
     ],
     "Task286": [
          10,
          336,
          97,
          479
     ],
     "Task287": [
          10,
          348,
          82,
          442
     ],
     "Task288": [
          10,
          336,
          60,
          441
     ],
     "Task289": [
          2,
          348,
          5,
          457
     ],
     "Task290": [
          2,
          348,
          24,
          470
     ],
     "Task291": [
          2,
          342,
          86,
          424
     ],
     "Task292": [
          1,
          342,
          4,
          435
     ],
     "Task293": [
          3,
          342,
          25,
          422
     ],
     "Task294": [
          2,
          342,
          35,
          401
     ],
     "Task295": [
          5,
          336,
          9,
          463
     ],
     "Task296": [
          11,
          336,
          79,
          409
     ],
     "Task297": [
          1,
          336,
          83,
          464
     ],
     "Task298": [
          4,
          348,
          91,
          488
     ],
     "Task299": [
          6,
          348,
          21,
          447
     ],
     "Task300": [
          5,
          348,
          91,
          497
     ],
     "Task301": [
          2,
          348,
          26,
          474
     ],
     "Task302": [
          6,
          342,
          89,
          466
     ],
     "Task303": [
          8,
          336,
          5,
          500
     ],
     "Task304": [
          3,
          348,
          6,
          484
     ],
     "Task305": [
          7,
          342,
          33,
          426
     ],
     "Task306": [
          7,
          336,
          78,
          426
     ],
     "Task307": [
          1,
          348,
          39,
          407
     ],
     "Task308": [
          11,
          348,
          99,
          445
     ],
     "Task309": [
          4,
          348,
          38,
          400
     ],
     "Task310": [
          3,
          342,
          56,
          436
     ],
     "Task311": [
          2,
          336,
          66,
          470
     ],
     "Task312": [
          10,
          342,
          68,
          412
     ],
     "Task313": [
          7,
          336,
          53,
          482
     ],
     "Task314": [
          7,
          348,
          96,
          479
     ],
     "Task315": [
          5,
          336,
          88,
          407
     ],
     "Task316": [
          7,
          336,
          67,
          465
     ],
     "Task317": [
          10,
          348,
          93,
          446
     ],
     "Task318": [
          1,
          336,
          71,
          443
     ],
     "Task319": [
          2,
          336,
          81,
          416
     ],
     "Task320": [
          4,
          336,
          28,
          411
     ],
     "Task321": [
          9,
          342,
          84,
          438
     ],
     "Task322": [
          3,
          342,
          28,
          451
     ],
     "Task323": [
          5,
          348,
          42,
          438
     ],
     "Task324": [
          3,
          342,
          41,
          437
     ],
     "Task325": [
          9,
          336,
          35,
          467
     ],
     "Task326": [
          4,
          336,
          79,
          481
     ],
     "Task327": [
          4,
          342,
          37,
          492
     ],
     "Task328": [
          3,
          336,
          22,
          498
     ],
     "Task329": [
          11,
          348,
          8,
          452
     ],
     "Task330": [
          3,
          348,
          67,
          444
     ],
     "Task331": [
          2,
          342,
          73,
          403
     ],
     "Task332": [
          11,
          342,
          77,
          451
     ],
     "Task333": [
          3,
          348,
          78,
          437
     ],
     "Task334": [
          9,
          342,
          47,
          470
     ],
     "Task335": [
          8,
          342,
          46,
          446
     ],
     "Task336": [
          5,
          336,
          5,
          496
     ],
     "Task337": [
          7,
          342,
          50,
          410
     ],
     "Task338": [
          4,
          336,
          16,
          403
     ],
     "Task339": [
          6,
          336,
          81,
          494
     ],
     "Task340": [
          10,
          336,
          18,
          480
     ],
     "Task341": [
          8,
          348,
          64,
          459
     ],
     "Task342": [
          4,
          342,
          43,
          417
     ],
     "Task343": [
          6,
          348,
          10,
          430
     ],
     "Task344": [
          10,
          342,
          73,
          483
     ],
     "Task345": [
          8,
          336,
          7,
          405
     ],
     "Task346": [
          3,
          336,
          57,
          487
     ],
     "Task347": [
          9,
          348,
          89,
          464
     ],
     "Task348": [
          11,
          348,
          62,
          483
     ],
     "Task349": [
          8,
          342,
          96,
          427
     ],
     "Task350": [
          1,
          336,
          11,
          437
     ],
     "Task351": [
          2,
          342,
          100,
          423
     ],
     "Task352": [
          1,
          336,
          68,
          412
     ],
     "Task353": [
          8,
          336,
          71,
          464
     ],
     "Task354": [
          11,
          336,
          3,
          405
     ],
     "Task355": [
          9,
          336,
          80,
          490
     ],
     "Task356": [
          4,
          342,
          75,
          458
     ],
     "Task357": [
          6,
          336,
          5,
          465
     ],
     "Task358": [
          4,
          342,
          62,
          408
     ],
     "Task359": [
          9,
          348,
          11,
          454
     ],
     "Task360": [
          8,
          342,
          43,
          492
     ],
     "Task361": [
          4,
          348,
          12,
          478
     ],
     "Task362": [
          7,
          348,
          12,
          456
     ],
     "Task363": [
          5,
          342,
          58,
          466
     ],
     "Task364": [
          3,
          336,
          13,
          458
     ],
     "Task365": [
          10,
          342,
          48,
          465
     ],
     "Task366": [
          9,
          336,
          1,
          459
     ],
     "Task367": [
          2,
          348,
          99,
          416
     ],
     "Task368": [
          4,
          336,
          72,
          450
     ],
     "Task369": [
          4,
          336,
          95,
          457
     ],
     "Task370": [
          7,
          336,
          74,
          473
     ],
     "Task371": [
          11,
          336,
          23,
          423
     ],
     "Task372": [
          5,
          336,
          7,
          488
     ],
     "Task373": [
          10,
          336,
          15,
          494
     ],
     "Task374": [
          1,
          348,
          3,
          418
     ],
     "Task375": [
          9,
          342,
          51,
          492
     ],
     "Task376": [
          7,
          336,
          17,
          492
     ],
     "Task377": [
          8,
          336,
          72,
          417
     ],
     "Task378": [
          6,
          348,
          2,
          480
     ],
     "Task379": [
          9,
          348,
          20,
          452
     ],
     "Task380": [
          5,
          348,
          57,
          487
     ],
     "Task381": [
          3,
          342,
          89,
          445
     ],
     "Task382": [
          5,
          348,
          27,
          422
     ],
     "Task383": [
          6,
          336,
          94,
          430
     ],
     "Task384": [
          11,
          336,
          8,
          420
     ],
     "Task385": [
          1,
          336,
          76,
          423
     ],
     "Task386": [
          11,
          342,
          93,
          461
     ],
     "Task387": [
          9,
          348,
          62,
          485
     ],
     "Task388": [
          11,
          336,
          81,
          464
     ],
     "Task389": [
          4,
          342,
          47,
          485
     ],
     "Task390": [
          4,
          342,
          96,
          483
     ],
     "Task391": [
          8,
          348,
          76,
          423
     ],
     "Task392": [
          3,
          336,
          13,
          419
     ],
     "Task393": [
          2,
          342,
          42,
          500
     ],
     "Task394": [
          10,
          348,
          66,
          472
     ],
     "Task395": [
          8,
          348,
          71,
          404
     ],
     "Task396": [
          2,
          342,
          78,
          415
     ],
     "Task397": [
          6,
          342,
          45,
          420
     ],
     "Task398": [
          2,
          348,
          28,
          426
     ],
     "Task399": [
          4,
          342,
          23,
          438
     ]
}